hypermea/core/__init__.py
hypermea/core/affordances/__init__.py
hypermea/core/affordances/rfc6861/__init__.py
hypermea/core/affordances/rfc6861/_common.py
hypermea/core/affordances/rfc6861/create_form.py
hypermea/core/affordances/rfc6861/edit_form.py
hypermea/core/domain/__init__.py
hypermea/core/domain/relation.py
hypermea/core/domain/resource_model.py
hypermea/core/domain/resource_ref.py
hypermea/core/gateway/__init__.py
hypermea/core/hooks/__init__.py
hypermea/core/href/__init__.py
hypermea/core/logging/__init__.py
hypermea/core/logging/hooks.py
hypermea/core/logging/log_setup.py
hypermea/core/logging/setup.py
hypermea/core/logging/smtp_handler.py
hypermea/core/logging/trace/__init__.py
hypermea/core/logging/trace/decorators.py
hypermea/core/logging/trace/trace_level.py
hypermea/core/render/__init__.py
hypermea/core/render/context.py
hypermea/core/render/embedder.py
hypermea/core/render/hal_renderer.py
hypermea/core/render/linker.py
hypermea/core/response/__init__.py
hypermea/core/settings/__init__.py
hypermea/core/settings/promoter.py
hypermea/core/utils/__init__.py
hypermea/core/utils/emoji.py
hypermea/core/utils/singleton.py
hypermea/core/validation/__init__.py
hypermea/core/validation/validator.py
hypermea_core-0.9.51.dist-info/METADATA
hypermea_core-0.9.51.dist-info/WHEEL
hypermea_core-0.9.51.dist-info/top_level.txt
hypermea_core-0.9.51.dist-info/RECORD
