Metadata-Version: 2.1
Name: hypermea-core
Version: 0.9.51
Summary: The core library used by hypermea APIs.
Home-page: https://github.com/pointw-dev/hypermea
Author: Michael Ottoson
Author-email: michael@pointw.com
License: MIT
Classifier: Development Status :: 4 - Beta
Classifier: License :: OSI Approved :: MIT License
Classifier: Programming Language :: Python :: 3
Classifier: Operating System :: OS Independent
Classifier: Framework :: Flask
Classifier: Intended Audience :: Developers
Classifier: Topic :: Internet :: WWW/HTTP :: HTTP Servers
Classifier: Topic :: Software Development :: Code Generators
Classifier: Topic :: Utilities
Requires-Dist: Eve ==2.2.0
Requires-Dist: pydantic ==2.11.3
Requires-Dist: inflect ==4.1.0
